serverstats/__init__.py
serverstats/serverstats.py
serverstats-0.2.0.dist-info/LICENSE
serverstats-0.2.0.dist-info/METADATA
serverstats-0.2.0.dist-info/WHEEL
serverstats-0.2.0.dist-info/dependency_links.txt
serverstats-0.2.0.dist-info/entry_points.txt
serverstats-0.2.0.dist-info/top_level.txt
serverstats-0.2.0.dist-info/RECORD
