Metadata-Version: 2.1
Name: serverstats
Version: 0.2.0
Summary: Collect important system metrics from a server and log them
Home-page: https://github.com/deep-compute/serverstats
Author: Deep Compute, LLC
Author-email: contact@deepcompute.com
License: MIT
Keywords: serverstats
Platform: UNKNOWN
Classifier: Programming Language :: Python :: 2.7
Classifier: Environment :: Console
Classifier: Intended Audience :: Developers
Classifier: License :: OSI Approved :: MIT License
Requires-Dist: basescript (==0.2.0)
Requires-Dist: psutil (==5.4.3)
Requires-Dist: deeputil (==0.2.5)
Requires-Dist: flatten-dict (==0.0.2)
